<?xml version="1.0" encoding="UTF-8"?><oschina>	
		  <tweet>
    <id>6065727</id>
	<body><![CDATA[
		蹲个厕所，汗流的比尿还多        	]]></body>
    <author><![CDATA[lieefu]]></author>
	<authorid>2349187</authorid>
    <appclient>4</appclient>
    <commentCount>1</commentCount>
	<portrait>http://192.168.79.254:8080/oschina/images/uploads/user/1174/2349187_50.png?t=1434521938000</portrait>
    <pubDate>2015-07-17 13:05:30</pubDate>
	<imgSmall>http://192.168.79.254:8080/oschina/images/uploads/space/2015/0717/130531_ppP5_2349187_thumb.jpg</imgSmall>
	<imgBig>http://192.168.79.254:8080/oschina/images/uploads/space/2015/0717/130531_ppP5_2349187.jpg</imgBig>
    <attach></attach>
    
    	<likeCount>0</likeCount>
	<isLike>0</isLike>
	<likeList>
					</likeList>
  </tweet>
</oschina>	
