<?xml version="1.0" encoding="UTF-8"?>        <oschina>
    <allCount>2</allCount>
    <pagesize>2</pagesize>
    <comments>
                    												                                                <comment>
                <id>6052890</id>
                <portrait>http://192.168.79.254:8080/oschina/images/uploads/user/437/875838_50.jpg?t=1417157880000</portrait>
                <author><![CDATA[哈莱米修]]></author>
                <authorid>875838</authorid>
                <content><![CDATA[不是雾霾，是霾[阴险]]]></content>
                <pubDate>2015-07-16 09:33:51</pubDate>
                                    <appclient>0</appclient>
                                                            </comment>
                    												                                                <comment>
                <id>6052489</id>
                <portrait>http://192.168.79.254:8080/oschina/images/uploads/user/128/256376_50.jpg?t=1433831619000</portrait>
                <author><![CDATA[洛水]]></author>
                <authorid>256376</authorid>
                <content><![CDATA[是。]]></content>
                <pubDate>2015-07-16 09:02:10</pubDate>
                                    <appclient>0</appclient>
                                                            </comment>
            </comments>
    </oschina>