<?xml version="1.0" encoding="UTF-8"?>        <oschina>
    <allCount>39</allCount>
    <pagesize>20</pagesize>
    <comments>
                    												                                                <comment>
                <id>6064939</id>
                <portrait>http://192.168.79.254:8080/oschina/images/uploads/user/521/1043184_50.jpg?t=1431744842000</portrait>
                <author><![CDATA[blu10ph]]></author>
                <authorid>1043184</authorid>
                <content><![CDATA[@naomi_lisa 能啊，没人说不能啊，有蛋疼的时间多挣点钱，以后日子也好过点不是，能给爱的人提供更好的条件你心里不也舒服吗？~]]></content>
                <pubDate>2015-07-17 11:38:19</pubDate>
                                    <appclient>5</appclient>
                                                            </comment>
                    												                                                <comment>
                <id>6063628</id>
                <portrait>http://192.168.79.254:8080/oschina/images/uploads/user/888/1776864_50.jpg?t=1420532344000</portrait>
                <author><![CDATA[naomi_lisa]]></author>
                <authorid>1776864</authorid>
                <content><![CDATA[@blu10ph ...说得好实际，穷人就不能爱吗]]></content>
                <pubDate>2015-07-17 10:10:17</pubDate>
                                    <appclient>4</appclient>
                                                            </comment>
                    												                                                <comment>
                <id>6063617</id>
                <portrait>http://192.168.79.254:8080/oschina/images/uploads/user/888/1776864_50.jpg?t=1420532344000</portrait>
                <author><![CDATA[naomi_lisa]]></author>
                <authorid>1776864</authorid>
                <content><![CDATA[@大象Jepson 谢谢，现在好很多了]]></content>
                <pubDate>2015-07-17 10:09:39</pubDate>
                                    <appclient>4</appclient>
                                                            </comment>
                    												                                                <comment>
                <id>6062258</id>
                <portrait>http://192.168.79.254:8080/oschina/images/uploads/user/521/1043184_50.jpg?t=1431744842000</portrait>
                <author><![CDATA[blu10ph]]></author>
                <authorid>1043184</authorid>
                <content><![CDATA[多挣钱，这样你的机会大一点~]]></content>
                <pubDate>2015-07-17 07:23:55</pubDate>
                                    <appclient>5</appclient>
                                                            </comment>
                    												                                                <comment>
                <id>6052504</id>
                <portrait></portrait>
                <author><![CDATA[大象Jepson]]></author>
                <authorid>2385422</authorid>
                <content><![CDATA[安慰一下[拥抱]]]></content>
                <pubDate>2015-07-16 09:03:55</pubDate>
                                    <appclient>0</appclient>
                                                            </comment>
                    												                                                <comment>
                <id>6051070</id>
                <portrait>http://192.168.79.254:8080/oschina/images/uploads/user/67/135555_50.jpg?t=1372839661000</portrait>
                <author><![CDATA[霡霂]]></author>
                <authorid>135555</authorid>
                <content><![CDATA[回复 @霡霂 : 我这还有用，可以搞基。]]></content>
                <pubDate>2015-07-15 21:21:54</pubDate>
                                    <appclient>0</appclient>
                                                            </comment>
                    												                                                <comment>
                <id>6049919</id>
                <portrait>http://192.168.79.254:8080/oschina/images/uploads/user/888/1776864_50.jpg?t=1420532344000</portrait>
                <author><![CDATA[naomi_lisa]]></author>
                <authorid>1776864</authorid>
                <content><![CDATA[@霡霂 你割了？]]></content>
                <pubDate>2015-07-15 18:17:03</pubDate>
                                    <appclient>4</appclient>
                                                            </comment>
                    												                                                <comment>
                <id>6046119</id>
                <portrait>http://192.168.79.254:8080/oschina/images/uploads/user/67/135555_50.jpg?t=1372839661000</portrait>
                <author><![CDATA[霡霂]]></author>
                <authorid>135555</authorid>
                <content><![CDATA[割了吧，卵并没有什么用。]]></content>
                <pubDate>2015-07-15 13:54:40</pubDate>
                                    <appclient>0</appclient>
                                                            </comment>
                    												                                                <comment>
                <id>6046066</id>
                <portrait>http://192.168.79.254:8080/oschina/images/uploads/user/103/207426_50.jpg?t=1375761582000</portrait>
                <author><![CDATA[bigtiger02]]></author>
                <authorid>207426</authorid>
                <content><![CDATA[求av？]]></content>
                <pubDate>2015-07-15 13:49:56</pubDate>
                                    <appclient>0</appclient>
                                                            </comment>
                    												                                                <comment>
                <id>6045912</id>
                <portrait>http://192.168.79.254:8080/oschina/images/uploads/user/362/724344_50.png?t=1430358996000</portrait>
                <author><![CDATA[花间小酌]]></author>
                <authorid>724344</authorid>
                <content><![CDATA[大老爷们 求什么安慰]]></content>
                <pubDate>2015-07-15 13:39:51</pubDate>
                                    <appclient>0</appclient>
                                                            </comment>
                    												                                                <comment>
                <id>6044948</id>
                <portrait>http://192.168.79.254:8080/oschina/images/uploads/user/435/870856_50.jpg?t=1419050055000</portrait>
                <author><![CDATA[一曲]]></author>
                <authorid>870856</authorid>
                <content><![CDATA[嗯，多喝热火]]></content>
                <pubDate>2015-07-15 11:51:45</pubDate>
                                    <appclient>0</appclient>
                                                            </comment>
                    												                                                <comment>
                <id>6043801</id>
                <portrait>http://192.168.79.254:8080/oschina/images/uploads/user/1004/2008084_50.jpg?t=1431506806000</portrait>
                <author><![CDATA[感觉太煽情]]></author>
                <authorid>2008084</authorid>
                <content><![CDATA[我是来看评论的，不过还是挺欢迎你重回单身狗行列，我代表广大单身狗欢迎你~]]></content>
                <pubDate>2015-07-15 10:48:54</pubDate>
                                    <appclient>0</appclient>
                                                            </comment>
                    												                                                <comment>
                <id>6043569</id>
                <portrait>http://192.168.79.254:8080/oschina/images/uploads/user/56/113186_50.jpg?t=1368156098000</portrait>
                <author><![CDATA[铂金苍鹰]]></author>
                <authorid>113186</authorid>
                <content><![CDATA[求AV？]]></content>
                <pubDate>2015-07-15 10:37:24</pubDate>
                                    <appclient>0</appclient>
                                                            </comment>
                    												                                                <comment>
                <id>6041995</id>
                <portrait>http://192.168.79.254:8080/oschina/images/uploads/user/1206/2413202_50.jpg?t=1436855886000</portrait>
                <author><![CDATA[奔跑中]]></author>
                <authorid>2413202</authorid>
                <content><![CDATA[@naomi_lisa 所以咯]]></content>
                <pubDate>2015-07-15 08:58:50</pubDate>
                                    <appclient>4</appclient>
                                                            </comment>
                    												                                                <comment>
                <id>6041841</id>
                <portrait>http://192.168.79.254:8080/oschina/images/uploads/user/126/253469_50.jpg?t=1422362476000</portrait>
                <author><![CDATA[稻草鸟人]]></author>
                <authorid>253469</authorid>
                <content><![CDATA[@naomi_lisa 哦....那你去买个充气的话，也不贵]]></content>
                <pubDate>2015-07-15 08:44:21</pubDate>
                                    <appclient>0</appclient>
                                                            </comment>
                    												                                                <comment>
                <id>6041786</id>
                <portrait>http://192.168.79.254:8080/oschina/images/uploads/user/888/1776864_50.jpg?t=1420532344000</portrait>
                <author><![CDATA[naomi_lisa]]></author>
                <authorid>1776864</authorid>
                <content><![CDATA[@奔跑中 哈哈，拉倒吧]]></content>
                <pubDate>2015-07-15 08:37:36</pubDate>
                                    <appclient>4</appclient>
                                                            </comment>
                    												                                                <comment>
                <id>6041469</id>
                <portrait>http://192.168.79.254:8080/oschina/images/uploads/user/428/857780_50.jpg?t=1388468572000</portrait>
                <author><![CDATA[G_Young]]></author>
                <authorid>857780</authorid>
                <content><![CDATA[@阿信sxq 是的。很长。]]></content>
                <pubDate>2015-07-15 01:53:12</pubDate>
                                    <appclient>3</appclient>
                                                            </comment>
                    												                                                <comment>
                <id>6040952</id>
                <portrait>http://192.168.79.254:8080/oschina/images/uploads/user/1131/2263657_50.jpg?t=1436825880000</portrait>
                <author><![CDATA[拿砖拍]]></author>
                <authorid>2263657</authorid>
                <content><![CDATA[马上开始一段新的]]></content>
                <pubDate>2015-07-14 22:48:08</pubDate>
                                    <appclient>3</appclient>
                                                            </comment>
                    												                                                <comment>
                <id>6040772</id>
                <portrait>http://192.168.79.254:8080/oschina/images/uploads/user/704/1409541_50.jpg?t=1435251410000</portrait>
                <author><![CDATA[zigzagroad]]></author>
                <authorid>1409541</authorid>
                <content><![CDATA[经历又丰富了。]]></content>
                <pubDate>2015-07-14 22:14:48</pubDate>
                                    <appclient>3</appclient>
                                                            </comment>
                    												                                                <comment>
                <id>6040610</id>
                <portrait>http://192.168.79.254:8080/oschina/images/uploads/user/466/932586_50.PNG?t=1423475532000</portrait>
                <author><![CDATA[阿信sxq]]></author>
                <authorid>932586</authorid>
                <content><![CDATA[不要伤心了，我曾经也经历过，到后来你会发现————这种日子还很长]]></content>
                <pubDate>2015-07-14 21:50:26</pubDate>
                                    <appclient>0</appclient>
                                                            </comment>
            </comments>
    </oschina>