<?xml version="1.0" encoding="UTF-8"?>        <oschina>
    <allCount>53</allCount>
    <pagesize>20</pagesize>
    <comments>
                    												                                                <comment>
                <id>6066390</id>
                <portrait>http://192.168.79.254:8080/oschina/images/uploads/user/508/1016595_50.png?t=1411376058000</portrait>
                <author><![CDATA[18号]]></author>
                <authorid>1016595</authorid>
                <content><![CDATA[躺着拿钱的专业]]></content>
                <pubDate>2015-07-17 14:05:13</pubDate>
                                    <appclient>0</appclient>
                                                            </comment>
                    												                                                <comment>
                <id>6065701</id>
                <portrait>http://192.168.79.254:8080/oschina/images/uploads/user/112/224195_50.bmp?t=1436677341000</portrait>
                <author><![CDATA[Jweb]]></author>
                <authorid>224195</authorid>
                <content><![CDATA[动漫]]></content>
                <pubDate>2015-07-17 13:01:34</pubDate>
                                    <appclient>0</appclient>
                                                            </comment>
                    												                                                <comment>
                <id>6065254</id>
                <portrait>http://192.168.79.254:8080/oschina/images/uploads/user/584/1169894_50.jpg?t=1428071188000</portrait>
                <author><![CDATA[wp0615032]]></author>
                <authorid>1169894</authorid>
                <content><![CDATA[木工]]></content>
                <pubDate>2015-07-17 12:04:41</pubDate>
                                    <appclient>3</appclient>
                                                            </comment>
                    												                                                <comment>
                <id>6064937</id>
                <portrait>http://192.168.79.254:8080/oschina/images/uploads/user/1156/2312365_50.jpg?t=1422453216000</portrait>
                <author><![CDATA[YUKIANDI]]></author>
                <authorid>2312365</authorid>
                <content><![CDATA[软件工程。。。]]></content>
                <pubDate>2015-07-17 11:38:05</pubDate>
                                    <appclient>3</appclient>
                                                            </comment>
                    												                                                <comment>
                <id>6063281</id>
                <portrait>http://192.168.79.254:8080/oschina/images/uploads/user/996/1993951_50.jpg?t=1414459620000</portrait>
                <author><![CDATA[低俗如我]]></author>
                <authorid>1993951</authorid>
                <content><![CDATA[音乐]]></content>
                <pubDate>2015-07-17 09:46:34</pubDate>
                                    <appclient>0</appclient>
                                                            </comment>
                    												                                                <comment>
                <id>6062454</id>
                <portrait>http://192.168.79.254:8080/oschina/images/uploads/user/931/1863541_50.jpg?t=1426074764000</portrait>
                <author><![CDATA[Flygend]]></author>
                <authorid>1863541</authorid>
                <content><![CDATA[终极奥义]]></content>
                <pubDate>2015-07-17 08:34:56</pubDate>
                                    <appclient>4</appclient>
                                                            </comment>
                    												                                                <comment>
                <id>6062259</id>
                <portrait>http://192.168.79.254:8080/oschina/images/uploads/user/35/70817_50.jpg?t=1386327418000</portrait>
                <author><![CDATA[卜库塔]]></author>
                <authorid>70817</authorid>
                <content><![CDATA[数学]]></content>
                <pubDate>2015-07-17 07:25:10</pubDate>
                                    <appclient>3</appclient>
                                                            </comment>
                    												                                                <comment>
                <id>6060320</id>
                <portrait>http://192.168.79.254:8080/oschina/images/uploads/user/362/725743_50.jpg?t=1417361059000</portrait>
                <author><![CDATA[松子玉米烙]]></author>
                <authorid>725743</authorid>
                <content><![CDATA[化学]]></content>
                <pubDate>2015-07-16 19:07:55</pubDate>
                                    <appclient>0</appclient>
                                                            </comment>
                    												                                                <comment>
                <id>6059275</id>
                <portrait>http://192.168.79.254:8080/oschina/images/uploads/user/1123/2246527_50.jpg?t=1414294210000</portrait>
                <author><![CDATA[渺渺一粟]]></author>
                <authorid>2246527</authorid>
                <content><![CDATA[回复 @南派三叔 : 刘慈欣你懂么？]]></content>
                <pubDate>2015-07-16 17:31:36</pubDate>
                                    <appclient>0</appclient>
                                                            </comment>
                    												                                                <comment>
                <id>6059264</id>
                <portrait>http://192.168.79.254:8080/oschina/images/uploads/user/1123/2246527_50.jpg?t=1414294210000</portrait>
                <author><![CDATA[渺渺一粟]]></author>
                <authorid>2246527</authorid>
                <content><![CDATA[围棋十段]]></content>
                <pubDate>2015-07-16 17:30:50</pubDate>
                                    <appclient>0</appclient>
                                                            </comment>
                    												                                                <comment>
                <id>6058360</id>
                <portrait>http://192.168.79.254:8080/oschina/images/uploads/user/722/1444338_50.JPG?t=1390453582000</portrait>
                <author><![CDATA[wind9527]]></author>
                <authorid>1444338</authorid>
                <content><![CDATA[做木工]]></content>
                <pubDate>2015-07-16 16:31:37</pubDate>
                                    <appclient>0</appclient>
                                                            </comment>
                    												                                                <comment>
                <id>6056175</id>
                <portrait>http://192.168.79.254:8080/oschina/images/uploads/user/886/1773834_50.jpg?t=1423193228000</portrait>
                <author><![CDATA[薛定谔的悖论]]></author>
                <authorid>1773834</authorid>
                <content><![CDATA[看手相[抠鼻]]]></content>
                <pubDate>2015-07-16 14:11:11</pubDate>
                                    <appclient>0</appclient>
                                                            </comment>
                    												                                                <comment>
                <id>6055993</id>
                <portrait>http://192.168.79.254:8080/oschina/images/uploads/user/637/1274847_50.jpg?t=1436876443000</portrait>
                <author><![CDATA[空腔]]></author>
                <authorid>1274847</authorid>
                <content><![CDATA[回复 @Mr_K : 商学]]></content>
                <pubDate>2015-07-16 13:57:12</pubDate>
                                    <appclient>0</appclient>
                                                            </comment>
                    												                                                <comment>
                <id>6055992</id>
                <portrait>http://192.168.79.254:8080/oschina/images/uploads/user/637/1274847_50.jpg?t=1436876443000</portrait>
                <author><![CDATA[空腔]]></author>
                <authorid>1274847</authorid>
                <content><![CDATA[回复 @请叫我Mr_Liu : 国防科技！]]></content>
                <pubDate>2015-07-16 13:57:03</pubDate>
                                    <appclient>0</appclient>
                                                            </comment>
                    												                                                <comment>
                <id>6055991</id>
                <portrait>http://192.168.79.254:8080/oschina/images/uploads/user/637/1274847_50.jpg?t=1436876443000</portrait>
                <author><![CDATA[空腔]]></author>
                <authorid>1274847</authorid>
                <content><![CDATA[回复 @zp-wmhx : 农学]]></content>
                <pubDate>2015-07-16 13:56:48</pubDate>
                                    <appclient>0</appclient>
                                                            </comment>
                    												                                                <comment>
                <id>6055989</id>
                <portrait>http://192.168.79.254:8080/oschina/images/uploads/user/637/1274847_50.jpg?t=1436876443000</portrait>
                <author><![CDATA[空腔]]></author>
                <authorid>1274847</authorid>
                <content><![CDATA[回复 @muly : 表演学]]></content>
                <pubDate>2015-07-16 13:56:41</pubDate>
                                    <appclient>0</appclient>
                                                            </comment>
                    												                                                <comment>
                <id>6055811</id>
                <portrait>http://192.168.79.254:8080/oschina/images/uploads/user/428/857780_50.jpg?t=1388468572000</portrait>
                <author><![CDATA[G_Young]]></author>
                <authorid>857780</authorid>
                <content><![CDATA[哲学。]]></content>
                <pubDate>2015-07-16 13:43:02</pubDate>
                                    <appclient>3</appclient>
                                                            </comment>
                    												                                                <comment>
                <id>6055416</id>
                <portrait>http://192.168.79.254:8080/oschina/images/uploads/user/1167/2334610_50.jpg?t=1437101023000</portrait>
                <author><![CDATA[喜羊羊同学o]]></author>
                <authorid>2334610</authorid>
                <content><![CDATA[音乐！[拳头]]]></content>
                <pubDate>2015-07-16 12:57:30</pubDate>
                                    <appclient>3</appclient>
                                                            </comment>
                    												                                                <comment>
                <id>6055160</id>
                <portrait>http://192.168.79.254:8080/oschina/images/uploads/user/109/219762_50.gif?t=1412940619000</portrait>
                <author><![CDATA[zp-wmhx]]></author>
                <authorid>219762</authorid>
                <content><![CDATA[种菜]]></content>
                <pubDate>2015-07-16 12:07:34</pubDate>
                                    <appclient>0</appclient>
                                                            </comment>
                    												                                                <comment>
                <id>6054211</id>
                <portrait>http://192.168.79.254:8080/oschina/images/uploads/user/514/1028646_50.jpg?t=1377234516000</portrait>
                <author><![CDATA[muly]]></author>
                <authorid>1028646</authorid>
                <content><![CDATA[玩游戏，睡觉，主演av]]></content>
                <pubDate>2015-07-16 10:56:43</pubDate>
                                    <appclient>0</appclient>
                                                            </comment>
            </comments>
    </oschina>