<?xml version="1.0" encoding="UTF-8"?>        <oschina>
    <allCount>10</allCount>
    <pagesize>10</pagesize>
    <comments>
                    												                                                <comment>
                <id>6065247</id>
                <portrait>http://192.168.79.254:8080/oschina/images/uploads/user/362/724344_50.png?t=1430358996000</portrait>
                <author><![CDATA[花间小酌]]></author>
                <authorid>724344</authorid>
                <content><![CDATA[回复 @大菲 : [偷笑] 大众女神的宿命]]></content>
                <pubDate>2015-07-17 12:03:32</pubDate>
                                    <appclient>0</appclient>
                                                            </comment>
                    												                                                <comment>
                <id>6065032</id>
                <portrait>http://192.168.79.254:8080/oschina/images/uploads/user/511/1022254_50.JPG?t=1431128269000</portrait>
                <author><![CDATA[ClassNotFound]]></author>
                <authorid>1022254</authorid>
                <content><![CDATA[请联系我]]></content>
                <pubDate>2015-07-17 11:45:16</pubDate>
                                    <appclient>0</appclient>
                                                            </comment>
                    												                                                <comment>
                <id>6064996</id>
                <portrait>http://192.168.79.254:8080/oschina/images/uploads/user/995/1991026_50.jpg?t=1416931477000</portrait>
                <author><![CDATA[大菲]]></author>
                <authorid>1991026</authorid>
                <content><![CDATA[@inmyfree 卧槽怎么又有我]]></content>
                <pubDate>2015-07-17 11:42:16</pubDate>
                                    <appclient>0</appclient>
                                                            </comment>
                    												                                                <comment>
                <id>6064867</id>
                <portrait>http://192.168.79.254:8080/oschina/images/uploads/user/1141/2283246_50.jpg?t=1417512921000</portrait>
                <author><![CDATA[kay_L_J_Y]]></author>
                <authorid>2283246</authorid>
                <content><![CDATA[回复 @inmyfree : 菲菲看不上我啊[流泪]]]></content>
                <pubDate>2015-07-17 11:33:01</pubDate>
                                    <appclient>0</appclient>
                                                            </comment>
                    												                                                <comment>
                <id>6064856</id>
                <portrait>http://192.168.79.254:8080/oschina/images/uploads/user/1141/2283246_50.jpg?t=1417512921000</portrait>
                <author><![CDATA[kay_L_J_Y]]></author>
                <authorid>2283246</authorid>
                <content><![CDATA[回复 @钛合金番薯 : 不要充气的[撇嘴]]]></content>
                <pubDate>2015-07-17 11:32:03</pubDate>
                                    <appclient>0</appclient>
                                                            </comment>
                    												                                                <comment>
                <id>6064850</id>
                <portrait>http://192.168.79.254:8080/oschina/images/uploads/user/1141/2283246_50.jpg?t=1417512921000</portrait>
                <author><![CDATA[kay_L_J_Y]]></author>
                <authorid>2283246</authorid>
                <content><![CDATA[回复 @CarlHuang : 不要充气的[撇嘴]]]></content>
                <pubDate>2015-07-17 11:31:49</pubDate>
                                    <appclient>0</appclient>
                                                            </comment>
                    												                                                <comment>
                <id>6064740</id>
                <portrait>http://192.168.79.254:8080/oschina/images/uploads/user/76/153537_50.jpg?t=1368196769000</portrait>
                <author><![CDATA[inmyfree]]></author>
                <authorid>153537</authorid>
                <content><![CDATA[@胖菲菲]]></content>
                <pubDate>2015-07-17 11:25:16</pubDate>
                                    <appclient>0</appclient>
                                                            </comment>
                    												                                                <comment>
                <id>6064735</id>
                <portrait></portrait>
                <author><![CDATA[32Er43]]></author>
                <authorid>2380431</authorid>
                <content><![CDATA[tong]]></content>
                <pubDate>2015-07-17 11:25:00</pubDate>
                                    <appclient>0</appclient>
                                                            </comment>
                    												                                                <comment>
                <id>6064708</id>
                <portrait>http://192.168.79.254:8080/oschina/images/uploads/user/579/1158264_50.jpg?t=1428042721000</portrait>
                <author><![CDATA[CarlHuang]]></author>
                <authorid>1158264</authorid>
                <content><![CDATA[淘宝呀.花样随便挑[色]]]></content>
                <pubDate>2015-07-17 11:23:23</pubDate>
                                    <appclient>0</appclient>
                                                            </comment>
                    												                                                <comment>
                <id>6064642</id>
                <portrait>http://192.168.79.254:8080/oschina/images/uploads/user/329/659525_50.jpg?t=1379396742000</portrait>
                <author><![CDATA[钛合金番薯]]></author>
                <authorid>659525</authorid>
                <content><![CDATA[上淘宝啊]]></content>
                <pubDate>2015-07-17 11:19:58</pubDate>
                                    <appclient>0</appclient>
                                                            </comment>
            </comments>
    </oschina>